CHANGES.rst
LICENSE.rst
MANIFEST.in
README.rst
bootstrap.py
buildout.cfg
setup.py
src/lineage/__init__.py
src/lineage.themeselection.egg-info/PKG-INFO
src/lineage.themeselection.egg-info/SOURCES.txt
src/lineage.themeselection.egg-info/dependency_links.txt
src/lineage.themeselection.egg-info/entry_points.txt
src/lineage.themeselection.egg-info/namespace_packages.txt
src/lineage.themeselection.egg-info/not-zip-safe
src/lineage.themeselection.egg-info/requires.txt
src/lineage.themeselection.egg-info/top_level.txt
src/lineage/themeselection/__init__.py
src/lineage/themeselection/action.py
src/lineage/themeselection/configure.zcml
src/lineage/themeselection/interfaces.py
src/lineage/themeselection/subscriber.py
src/lineage/themeselection/themingcontrolpanel.py
src/lineage/themeselection/upgrades.py
src/lineage/themeselection/profile/actions.xml
src/lineage/themeselection/profile/browserlayer.xml
src/lineage/themeselection/profile/metadata.xml
src/lineage/themeselection/uninstall/actions.xml
src/lineage/themeselection/uninstall/browserlayer.xml